donkit/vectorstore_loader/__init__.py
donkit/vectorstore_loader/chroma_loader.py
donkit/vectorstore_loader/milvus_loader.py
donkit/vectorstore_loader/qdrant_loader.py
donkit/vectorstore_loader/vectorstore_loader_abstract.py
donkit_vectorstore_loader-0.1.3.dist-info/METADATA
donkit_vectorstore_loader-0.1.3.dist-info/WHEEL
donkit_vectorstore_loader-0.1.3.dist-info/RECORD
