Metadata-Version: 2.3
Name: donkit-vectorstore-loader
Version: 0.1.3
Summary: Vectorstore upload helpers for Donkit RagOps
License: MIT
Author: Donkit AI
Author-email: opensource@donkit.ai
Requires-Python: >=3.12,<4.0
Classifier: License :: OSI Approved :: MIT License
Classifier: Programming Language :: Python :: 3
Classifier: Programming Language :: Python :: 3.12
Classifier: Programming Language :: Python :: 3.13
Requires-Dist: chromadb (>=1.0.20,<2.0.0)
Requires-Dist: langchain (>=0.3.27,<0.4.0)
Requires-Dist: langchain-core (>=0.3.79,<0.4.0)
Requires-Dist: loguru (>=0.7.3,<0.8.0)
Requires-Dist: pydantic (>=2.7.4,<3.0.0)
Requires-Dist: pymilvus (==2.6.0)
Requires-Dist: qdrant-client[fastembed] (>=1.15.1,<2.0.0)
